diagrams_exporters/__init__.py
diagrams_exporters/aws.py
diagrams_exporters/cli.py
diagrams_exporters-0.1.0a1.dist-info/LICENSE
diagrams_exporters-0.1.0a1.dist-info/METADATA
diagrams_exporters-0.1.0a1.dist-info/WHEEL
diagrams_exporters-0.1.0a1.dist-info/entry_points.txt
diagrams_exporters-0.1.0a1.dist-info/RECORD
