Metadata-Version: 2.1
Name: diagrams_exporters
Version: 0.1.0a1
Summary: export the metadata from existing tools, and generate the diagrams
License: MIT
Author: Anddd7
Author-email: anddd7@icloud.com
Requires-Python: >=3.12,<4.0
Classifier: License :: OSI Approved :: MIT License
Classifier: Programming Language :: Python :: 3
Classifier: Programming Language :: Python :: 3.12
Requires-Dist: click (>=8.1.7,<9.0.0)
Requires-Dist: diagrams-ext (==0.23.5a7)
Requires-Dist: diagrams-patterns (==0.1.0a1)
Requires-Dist: pydot (>=2.0.0,<3.0.0)
